{
  "title": "Tercera Entrada",
  "description": "Descripcion Corta",
  "images": [
    "assets/images/photo-2026-07-08-17-55-40.jpg"
  ],
  "body": "Lorem ipsum dolor sit amet, consectetur adipiscing elit. Curabitur eget bibendum magna, vitae ornare dolor. Donec maximus ultricies dictum. Praesent sit amet felis sed felis fermentum cursus. Morbi ac velit vulputate, tempus eros id, rutrum lectus. Vestibulum tincidunt urna ut eleifend vehicula. Sed ac augue suscipit, placerat leo vitae, pellentesque nulla. Maecenas metus sem, facilisis eu sem sit amet, gravida sodales lectus. Fusce non nisl pharetra, aliquam nisi eu, laoreet nisi. Sed volutpat eget neque sed porttitor. Fusce volutpat dolor sit amet sem fringilla, et interdum lectus tincidunt. Etiam a eleifend metus, sed pretium leo. Nunc finibus sollicitudin suscipit. Etiam aliquam sit amet urna et rhoncus. Nunc aliquet suscipit nisl, ut sodales magna. Curabitur aliquam suscipit euismod.\n\nMaecenas bibendum odio tortor, sit amet elementum justo placerat quis. Integer at libero quam. Aliquam non lorem eget arcu blandit sagittis sit amet congue magna. Curabitur eleifend vehicula blandit. Integer pellentesque orci id malesuada condimentum. Donec vel convallis massa. Fusce aliquam nibh non est fringilla, quis pellentesque libero porttitor. Curabitur non nulla et mi posuere euismod. Quisque vel tellus faucibus nunc fringilla euismod et a urna. Sed id convallis urna. Etiam quis urna velit. Nunc at lectus consequat, interdum metus ut, vulputate nisi.\n\nIn suscipit ligula ac purus tempus sodales. Ut eget arcu dui. Donec blandit a magna id interdum. In odio diam, vestibulum at ullamcorper non, convallis vel magna. Vestibulum id lectus pulvinar, scelerisque lorem ut, auctor libero. Duis ac tortor nec mauris malesuada lobortis et ac metus. Phasellus ac sodales ex. Nulla congue urna eu tortor volutpat, eu gravida risus vestibulum. Quisque dapibus mauris nec odio pharetra, vel pellentesque nulla vehicula.\n\nCras vehicula metus sed varius fermentum. Duis erat mi, ornare mattis purus et, fermentum faucibus tortor. Aliquam et dui risus. Nulla mattis, nibh non molestie vulputate, nisi justo ullamcorper dui, vitae blandit dolor nisi et nunc. Duis tincidunt quis quam vel tempor. Sed ultrices vulputate augue sed varius. Sed nec hendrerit arcu, dignissim pharetra sem. Nullam vel pretium ante.\n\nDonec vitae nunc purus. Etiam sit amet felis tortor. In et pellentesque arcu, aliquam semper nunc. Sed magna ante, vulputate eu tempor sed, imperdiet vel nulla. Vestibulum lobortis feugiat arcu, vitae vulputate nisl tempor vitae. Pellentesque habitant morbi tristique senectus et netus et malesuada fames ac turpis egestas. Duis egestas lectus vel eleifend porttitor. Pellentesque sit amet sem porta, condimentum mauris vel, consectetur libero. Fusce ultrices, sem id ornare auctor, sapien tellus fringilla quam, vitae tincidunt nisl tellus at orci. Aliquam sed mattis mauris.",
  "date": "2026-06-25T17:56:00.000-04:00"
}
